tele_upload/__inti__.py
tele_upload/cli.py
tele_upload/config.ini
tele_upload/main.py
tele_upload-0.0.2.dist-info/LICENSE
tele_upload-0.0.2.dist-info/METADATA
tele_upload-0.0.2.dist-info/WHEEL
tele_upload-0.0.2.dist-info/entry_points.txt
tele_upload-0.0.2.dist-info/top_level.txt
tele_upload-0.0.2.dist-info/RECORD
