Metadata-Version: 2.1
Name: tele-upload
Version: 0.0.2
Summary: upload files to your telegram channel or group with ypur telegram bot
Home-page: https://github.com/jakbin/tele-upload
Author: Jak Bin
Author-email: jakbin4747@gmail.com
License: UNKNOWN
Project-URL: Bug Tracker, https://github.com/jakbin/tele-upload/issues
Keywords: telegram,tele-upload,telegram-api,telegram-api-bot,telegram-file-upload,elegram-upload
Platform: UNKNOWN
Classifier: Programming Language :: Python :: 3.6
Classifier: License :: OSI Approved :: MIT License
Classifier: Natural Language :: English
Classifier: Operating System :: OS Independent
Requires-Python: >=3
License-File: LICENSE
Requires-Dist: requests
Requires-Dist: requests-toolbelt
Requires-Dist: tqdm
